wgl001package/__init__.py
wgl001package/module_file.py
wgl001package-0.1.0.dist-info/licenses/LICENSE.md
wgl001package-0.1.0.dist-info/METADATA
wgl001package-0.1.0.dist-info/WHEEL
wgl001package-0.1.0.dist-info/top_level.txt
wgl001package-0.1.0.dist-info/RECORD
